exactdelaypathfinder/__init__.py
exactdelaypathfinder/core.py
exactdelaypathfinder-0.1.4.dist-info/LICENSE
exactdelaypathfinder-0.1.4.dist-info/METADATA
exactdelaypathfinder-0.1.4.dist-info/WHEEL
exactdelaypathfinder-0.1.4.dist-info/top_level.txt
exactdelaypathfinder-0.1.4.dist-info/RECORD
