Metadata-Version: 2.1
Name: exactdelaypathfinder
Version: 0.1.4
Summary: Obtain paths with total delays equal or close to the user's requirements.
Home-page: UNKNOWN
Author: Jessela Baniqued, Daniel Bruce, Daniel Manso, Zachary Quevedo, Marvin Torres
Author-email: UNKNOWN
License: MIT
Platform: UNKNOWN
